setup.py
django_addview/__init__.py
django_addview/models.py
django_addview/tests.py
django_addview/views.py
django_addview.egg-info/PKG-INFO
django_addview.egg-info/SOURCES.txt
django_addview.egg-info/dependency_links.txt
django_addview.egg-info/not-zip-safe
django_addview.egg-info/requires.txt
django_addview.egg-info/top_level.txt
django_addview/management/__init__.py
django_addview/management/commands/__init__.py
django_addview/management/commands/_adder.py
django_addview/management/commands/_api.py
django_addview/management/commands/_config_loader.py
django_addview/management/commands/_utils.py
django_addview/management/commands/addview.py
django_addview/management/commands/tests.py
django_addview/management/commands/forms/__init__.py
django_addview/management/commands/forms/template_params.py
django_addview/management/commands/forms/urls_conf.py
django_addview/management/commands/forms/view_params.py
django_addview/management/commands/forms/view_type.py