Metadata-Version: 1.1
Name: django-addview
Version: 0.1.1
Summary: Adding views in Django as easy as pie.
Home-page: https://github.com/yakxxx/django-addview
Author: Jakub Kot
Author-email: yakxxx@gmail.com
License: BSD
Keywords: django,view,views,scaffold,cbv,application
Platform: UNKNOWN
Classifier: Framework :: Django
Classifier: Development Status :: 4 - Beta
Classifier: Topic :: Internet
Classifier: License :: OSI Approved :: BSD License
Classifier: Intended Audience :: Developers
Classifier: Environment :: Console :: Curses
Classifier: Programming Language :: Python :: 2.7
